{
    "milestones": [{
            "cartegraphID": "",
            "created": "09/12/2018",
            "dateCompleted": "09/12/2018",
            "dueDate": "06/21/2018",
            "milestoneID": "c9b6f9a0-b69e-11e8-930d-dd084cae8ed3",
            "milestoneName": "Acquire mahogany",
            "percentComplete": 100,
            "phaseID": "f805f1e0-b69d-11e8-930d-dd084cae8ed3",
            "projectID": "7341e860-b69d-11e8-930d-dd084cae8ed3"
        },
        {
            "cartegraphID": "",
            "created": "09/12/2018",
            "dateCompleted": "09/12/2018",
            "dueDate": "07/27/2018",
            "milestoneID": "d860f140-b69e-11e8-930d-dd084cae8ed3",
            "milestoneName": "Carve mahagony",
            "percentComplete": 100,
            "phaseID": "f805f1e0-b69d-11e8-930d-dd084cae8ed3",
            "projectID": "7341e860-b69d-11e8-930d-dd084cae8ed3"
        },
        {
            "cartegraphID": "",
            "created": "09/12/2018",
            "dateCompleted": "09/12/2018",
            "dueDate": "05/11/2018",
            "milestoneID": "6b234910-b69f-11e8-930d-dd084cae8ed3",
            "milestoneName": "Hire engineer",
            "percentComplete": 100,
            "phaseID": "c8e2af20-b69d-11e8-930d-dd084cae8ed3",
            "projectID": "7341e860-b69d-11e8-930d-dd084cae8ed3"
        },
        {
            "cartegraphID": "",
            "created": "09/12/2018",
            "dateCompleted": "",
            "dueDate": "06/21/2018",
            "milestoneID": "9a38a920-b69f-11e8-930d-dd084cae8ed3",
            "milestoneName": "Engineer completes design",
            "percentComplete": 0,
            "phaseID": "c8e2af20-b69d-11e8-930d-dd084cae8ed3",
            "projectID": "7341e860-b69d-11e8-930d-dd084cae8ed3"
        },
        {
            "cartegraphID": "",
            "created": "09/12/2018",
            "dateCompleted": "09/12/2018",
            "dueDate": "07/02/2016",
            "milestoneID": "7c141180-b6a1-11e8-930d-dd084cae8ed3",
            "milestoneName": "Talk",
            "percentComplete": 100,
            "phaseID": "615cc620-b6a1-11e8-930d-dd084cae8ed3",
            "projectID": "f9cbdd70-b6a0-11e8-930d-dd084cae8ed3"
        },
        {
            "cartegraphID": "",
            "created": "09/12/2018",
            "dateCompleted": "09/12/2018",
            "dueDate": "09/02/2016",
            "milestoneID": "83031f90-b6a1-11e8-930d-dd084cae8ed3",
            "milestoneName": "Talk some more",
            "percentComplete": 100,
            "phaseID": "615cc620-b6a1-11e8-930d-dd084cae8ed3",
            "projectID": "f9cbdd70-b6a0-11e8-930d-dd084cae8ed3"
        },
        {
            "cartegraphID": "",
            "created": "09/12/2018",
            "dateCompleted": "09/12/2018",
            "dueDate": "04/16/2016",
            "milestoneID": "1edc6e80-b6a2-11e8-930d-dd084cae8ed3",
            "milestoneName": "Make designs",
            "percentComplete": 100,
            "phaseID": "976022d0-b6a1-11e8-930d-dd084cae8ed3",
            "projectID": "f9cbdd70-b6a0-11e8-930d-dd084cae8ed3"
        },
        {
            "cartegraphID": "",
            "created": "09/12/2018",
            "dateCompleted": "09/12/2018",
            "dueDate": "06/23/2016",
            "milestoneID": "28cd9900-b6a2-11e8-930d-dd084cae8ed3",
            "milestoneName": "Talk about designs",
            "percentComplete": 100,
            "phaseID": "976022d0-b6a1-11e8-930d-dd084cae8ed3",
            "projectID": "f9cbdd70-b6a0-11e8-930d-dd084cae8ed3"
        }
    ]
}